[
    {
        "type": 0,
        "id": 0,
        "name": "单选题",
        "content": "（单选题）丙级建筑应依据地基主要受力层情况判断是否需要作变形验算，对于单一土层上的三层砖混结构条形基础，基础宽度为1.5m时，基地基主要受力层厚度可按下列哪个选项考虑?\r\n",
        "answer": [
            {
                "name": "A",
                "content": "1.5m",
                "isanswer": false
            },
            {
                "name": "B",
                "content": "3.0m\r",
                "isanswer": false
            },
            {
                "name": "C",
                "content": "4.5m",
                "isanswer": false
            },
            {
                "name": "D",
                "content": "5.0m\r",
                "isanswer": true
            }
        ],
        "detail": "\r\n【解析】根据《建筑地基基础设计规范》(GB 50007-2011)表3.0.3注1，地基主要受力层系指条形基础底面下深度为3b（b为基础底面宽度），独立基础下为1.5b，且厚度均不小于5m的范围（二层以下一般的民用建筑除外），本题为条形基础，3b=3×1.5m=4.5m，厚度取5m。",
        "index": 1
    },
    {
        "type": 0,
        "id": 0,
        "name": "单选题",
        "content": "（单选题）某单体建筑物主体结构的平面投影面积为700m2，荷载标准组合下建筑物竖向荷载为1.5×105kN，基础埋深约3m。持力层土质为中低压缩的黏性土，地基承载力特征值为150kPa。采用天然地基方案时，下列哪种基础形式最合理?\r\n",
        "answer": [
            {
                "name": "A",
                "content": "毛石混凝土扩展基础 ",
                "isanswer": false
            },
            {
                "name": "B",
                "content": "钢筋混凝土筏形基础\r",
                "isanswer": true
            },
            {
                "name": "C",
                "content": "钢筋混凝土十字交叉条形基础 ",
                "isanswer": false
            },
            {
                "name": "D",
                "content": "钢筋混凝土条形基础\r",
                "isanswer": false
            }
        ],
        "detail": "\r\n【解析】地基的平均荷载p=1.5×105/700=214kPa＞fak，不考虑宽度修正后的地基承载力特征值fak≈等150+1.6×18×(3-0.5)=222kPa，平均荷载p＜fa，采用筏形基础最合理，常识题，平均荷载超过地基承载力特征值一般采用筏形基础。",
        "index": 2
    },
    {
        "type": 0,
        "id": 0,
        "name": "单选题",
        "content": "（单选题）建筑物柱基平面尺寸3m×3m，埋深2m，内部发育有一溶洞，其与基础的相对关系如图所示，当溶洞的跨度L最大值接近下列何值时，可不考虑岩溶对地基稳定性的影响?\r\n<img src=\"https://gitee.com/yuebulv/picture/raw/master/yantu/20200416032410601.png\">",
        "answer": [
            {
                "name": "A",
                "content": "2m\r",
                "isanswer": false
            },
            {
                "name": "B",
                "content": "3m\r",
                "isanswer": false
            },
            {
                "name": "C",
                "content": "4m",
                "isanswer": false
            },
            {
                "name": "D",
                "content": "5m\r",
                "isanswer": true
            }
        ],
        "detail": "\r\n【解析】根据《建筑地基基础设计规范》(GB 50007-2011)第6.6.5条，对于完整、较完整的坚硬岩、较硬岩地基，当符合下列条件之一时，可不考虑岩溶对地基稳定性的影响：①洞体较小，基础底面尺寸大于洞的平面尺寸，并有足够的支承长度；②顶板岩石厚度大于或等于洞的跨度；即洞跨L≤5m，最大值为5m。",
        "index": 3
    },
    {
        "type": 0,
        "id": 0,
        "name": "单选题",
        "content": "（单选题）确定基础埋置深度时，可不考虑下列哪个因素?\r\n",
        "answer": [
            {
                "name": "A",
                "content": "基础的类型 ",
                "isanswer": false
            },
            {
                "name": "B",
                "content": "扩展基础的配筋量\r",
                "isanswer": true
            },
            {
                "name": "C",
                "content": "场地的冻结深度 ",
                "isanswer": false
            },
            {
                "name": "D",
                "content": "建筑物的抗震要求\r",
                "isanswer": false
            }
        ],
        "detail": "\r\n【解析】根据《建筑地基基础设计规范》(GB 50007-2011)第5.1.4条，基础埋置深度与基础的类型、建筑物的抗震要求有关，A、D正确；根据5.1.7条，基础埋置深度与场地的冻结深度有关，C正确；根据8.2.12条，扩展基础的配筋量基础底板的弯矩设计值和有效高度相关，与基础埋置深度无关，B错误。",
        "index": 4
    },
    {
        "type": 0,
        "id": 0,
        "name": "单选题",
        "content": "（单选题）某均匀地基上的高层建筑，采用直径60m的圆形筏基。用的准永久组合下，结构竖向荷载中心的偏心距不宜大于下列哪个选项?\r\n",
        "answer": [
            {
                "name": "A",
                "content": "0.18m",
                "isanswer": false
            },
            {
                "name": "B",
                "content": "0.30m\r",
                "isanswer": false
            },
            {
                "name": "C",
                "content": "0.36m",
                "isanswer": false
            },
            {
                "name": "D",
                "content": "0.75m\r",
                "isanswer": true
            }
        ],
        "detail": "\r\n【解析】根据《建筑地基基础设计规范》(GB 50007-2011)第8.4.2条，对单幢建筑物，在地基土比较均匀的条件下，基底平面形心宜与结构竖向永久载荷重心重合。当不能重合时，在作用的准永久组合下，偏心e应符合下式的规定：圆形基础的结论，案例多次考查过。13B03、06D06真题考点重现，应快速作答。<img src=\"https://gitee.com/yuebulv/picture/raw/master/yantu/20200416033315861.png\">",
        "index": 5
    },
    {
        "type": 0,
        "id": 0,
        "name": "单选题",
        "content": "（单选题）下列关于地基变形控制的说法，错误的是哪个选项?\r\n",
        "answer": [
            {
                "name": "A",
                "content": "独立基础的单层排架结构厂房，应控制柱基的沉降量\r",
                "isanswer": false
            },
            {
                "name": "B",
                "content": "剪力墙结构高层建筑，应控制基础整体倾斜\r",
                "isanswer": false
            },
            {
                "name": "C",
                "content": "条形基础的框架结构建筑，应控制基础局部倾斜\r",
                "isanswer": true
            },
            {
                "name": "D",
                "content": "框架筒体结构高层建筑，应控制筒体与框架柱之间的沉降差\r",
                "isanswer": false
            }
        ],
        "detail": "\r\n【解析】根据《建筑地基基础设计规范》(GB 50007-2011)第5.3.3条，对于框架结构和单层排架结构应由相邻柱基的沉降差控制，C错误。本考点为历年真题经常出题考点，应熟练掌握，单选题确定选项后其他的选项可以不看。",
        "index": 6
    },
    {
        "type": 0,
        "id": 0,
        "name": "单选题",
        "content": "（单选题）桩采用C30混凝土，验算桩的正截面受压承载力时，fc应选用下列哪个混凝土强度值?\r\n",
        "answer": [
            {
                "name": "A",
                "content": "30MPa",
                "isanswer": false
            },
            {
                "name": "B",
                "content": "20.1MPa\r",
                "isanswer": false
            },
            {
                "name": "C",
                "content": "14.3MPa",
                "isanswer": true
            },
            {
                "name": "D",
                "content": "1.43MPa\r",
                "isanswer": false
            }
        ],
        "detail": "\r\n【解析】根据《混凝土结构设计规范》(GB 50010-2010)(2015年版)表4.1.4-1，fc为混凝土抗压强度设计值C30混凝土对应的fc=14.3MPa；根据规范P286，第4.1.3条文说明fc=fck/1.4，轴心抗压强度标准值fck=0.88αc1αc2fcu，k，fcu，k为立方体抗压强度标准值即混凝土的标号，本题fc=0.88×0.76×30/1.4=14.3Mpa。本题为多次强度重要考点，应快速翻书查到。",
        "index": 7
    },
    {
        "type": 0,
        "id": 0,
        "name": "单选题",
        "content": "（单选题）某建筑工程，基坑深度20.0m，采用钻孔灌注桩基础，设计桩长36.0m。基桩纵向构造配筋的合理长度不宜小于下列哪个选项?\r\n",
        "answer": [
            {
                "name": "A",
                "content": "36.0m",
                "isanswer": false
            },
            {
                "name": "B",
                "content": "30.0m\r",
                "isanswer": true
            },
            {
                "name": "C",
                "content": "26.0m",
                "isanswer": false
            },
            {
                "name": "D",
                "content": "24.0m\r",
                "isanswer": false
            }
        ],
        "detail": "\r\n【解析】】根据《建筑地基基础设计规范》(GB 50007-2011)第8.5.3条第8款第4条，钻孔灌注桩构造钢筋的长度不宜小于桩长的2/3；桩施工在基坑开挖前完成时，其钢筋长度不宜小于基坑深度的1.5倍，故L≥36×2/3=24m且L≥20×1.5=30m。",
        "index": 8
    },
    {
        "type": 0,
        "id": 0,
        "name": "单选题",
        "content": "（单选题）某铁路桥梁，采用钻孔灌注桩群桩基础，设计桩径为1.2m。最外一排桩的中心至承台边缘的最小距离应为下列哪个选项?\r\n",
        "answer": [
            {
                "name": "A",
                "content": "0.36m",
                "isanswer": false
            },
            {
                "name": "B",
                "content": "0.50m\r",
                "isanswer": false
            },
            {
                "name": "C",
                "content": "0.96m",
                "isanswer": false
            },
            {
                "name": "D",
                "content": "1.10m\r",
                "isanswer": true
            }
        ],
        "detail": "\r\n【解析】根据《铁路桥涵地基和基础设计规范》(TB 10093-2017)第6.3.2条第4款，各类桩的承台边缘至最外一排桩的净距，桩径不大于1m时，净距不应小于0.5d，且不应小于0.25m；桩径大于1m时，净距不应小于0.3d，且不应小于0.5m，本题d=1.2m＞1m，净距L≥0.3×1.2=0.36m且L≥0.5m，故最小净距为0.5m，中心至边缘的距离，需要+桩的半径，为1.1m。本题有坑，规范上是净距，题目问的是中心至边缘的距离，审题非常关键。",
        "index": 9
    },
    {
        "type": 0,
        "id": 0,
        "name": "单选题",
        "content": "（单选题）下列选项中哪个说法符合预制桩锤击沉桩的施工原则？\r\n",
        "answer": [
            {
                "name": "A",
                "content": "重锤多击 ",
                "isanswer": false
            },
            {
                "name": "B",
                "content": "重锤轻击\r",
                "isanswer": true
            },
            {
                "name": "C",
                "content": "轻锤多击 ",
                "isanswer": false
            },
            {
                "name": "D",
                "content": "轻锤重击\r",
                "isanswer": false
            }
        ],
        "detail": "\r\n【解析】根据《建筑桩基技术规范》(JGJ 94-2008)，用锤击沉桩时，为防止桩受冲击应力过大而损坏，力求采用“重锤轻击”，落距小、频率高，不易产生回跃与桩头受损，桩容易入土，B正确；重锤多击，桩锤过重，易将桩打坏，A错误；轻锤多击，锤击过轻，不宜把桩打入，C错误； 如采用轻锤重击，锤击功能很大一部分被桩身吸收，桩不易打入，且桩头容易打碎，D错误；本知识点真题多次考查。",
        "index": 10
    },
    {
        "type": 0,
        "id": 0,
        "name": "单选题",
        "content": "（单选题）灌注桩施工遇有施工深度内存在较高水头的承压水时，不宜选取下列哪种施工工艺?\r\n",
        "answer": [
            {
                "name": "A",
                "content": "正循环回转钻进成孔灌注桩施工工艺\r",
                "isanswer": false
            },
            {
                "name": "B",
                "content": "反循环回转钻进成孔灌注桩施工工艺\r",
                "isanswer": false
            },
            {
                "name": "C",
                "content": "长螺旋钻孔压灌桩施工工艺\r",
                "isanswer": true
            },
            {
                "name": "D",
                "content": "泥浆护壁旋挖钻机成孔灌注桩施工工艺\r",
                "isanswer": false
            }
        ],
        "detail": "\r\n【解析】根据《建筑桩基技术规范》(JGJ 94-2008)P309第6.4条条文说明，长螺旋钻孔压灌桩施工适用于地下水位以上的黏性土、粉土、素填土、中等密实以上的砂土，属于非挤土成桩工艺，C错误。",
        "index": 11
    },
    {
        "type": 0,
        "id": 0,
        "name": "单选题",
        "content": "（单选题）下列哪种桩型的挤土效应最小?\r\n",
        "answer": [
            {
                "name": "A",
                "content": "实心预制方桩 ",
                "isanswer": false
            },
            {
                "name": "B",
                "content": "敞口预制管桩\r",
                "isanswer": true
            },
            {
                "name": "C",
                "content": "闭口钢管桩 ",
                "isanswer": false
            },
            {
                "name": "D",
                "content": "沉管灌注桩\r",
                "isanswer": false
            }
        ],
        "detail": "\r\n【解析】根据《建筑桩基技术规范》(JGJ 94-2008)第3.3.1条第2款，敞口预制管桩属于部分挤土桩；沉管灌注桩、实心预制方桩、闭口钢管桩属于挤土桩，故敞口预制管桩挤土效应最小。",
        "index": 12
    },
    {
        "type": 0,
        "id": 0,
        "name": "单选题",
        "content": "（单选题）对于二类和三类环境中，设计使用年限为50年的桩基础，下列关于其耐久性设计控制要求中，哪个选项符合规定?\r\n",
        "answer": [
            {
                "name": "A",
                "content": "位于2a类环境中的预应力混凝土管桩，其水泥用量不低于250kg/m3\r",
                "isanswer": false
            },
            {
                "name": "B",
                "content": "位于2b类环境中的钢筋混凝土桩基，其混凝土最大水灰比不得超过0.6\r",
                "isanswer": false
            },
            {
                "name": "C",
                "content": "位于三类环境中的钢筋混凝土桩基，使用碱活性骨料时，混凝土的最大碱含量不得超过3.0kg/m3\r",
                "isanswer": true
            },
            {
                "name": "D",
                "content": "位于三类环境中的预应力混凝土管桩，其最大裂缝宽度限值为0.2mm\r",
                "isanswer": false
            }
        ],
        "detail": "\r\n【解析】根据《建筑桩基技术规范》(JGJ 94-2008)根据表3.5.2，C正确；位于2b类环境中的钢筋混凝土桩基，其混凝土最大水灰比不得超过0.55，B错误；根据表3.5.2注2，预应力构件混凝土最小水泥用量为300kg/m3，A错误；根据表3.5.3，位于三类环境中的预应力混凝土管桩，其最大裂缝宽度限值为0mm，D错误。",
        "index": 13
    },
    {
        "type": 0,
        "id": 0,
        "name": "单选题",
        "content": "（单选题）下列关于桩基抗拔承载力的描述，哪个选项是正确的?\r\n",
        "answer": [
            {
                "name": "A",
                "content": "桩的抗拔承载力计算值与桩身配筋量有关\r",
                "isanswer": false
            },
            {
                "name": "B",
                "content": "桩的抗拔承载力计算值与桩周土体强度无关\r",
                "isanswer": false
            },
            {
                "name": "C",
                "content": "桩基的抗拔承载力计算值与地下水位无关\r",
                "isanswer": false
            },
            {
                "name": "D",
                "content": "轴心抗拔桩的正截面受拉承载力计算值与桩身混凝土抗拉强度无关\r",
                "isanswer": true
            }
        ],
        "detail": "\r\n【解析】根据《建筑桩基技术规范》(JGJ 94-2008)第5.4.5、5.4.6条，桩的抗拔承载力计算值与桩周土体强度、地下水位有关，与桩身配筋量无关，A、B、C错误；根据第5.8.7条，轴心抗拔桩的正截面受拉承载力计算值N≤fyAs+fpyApy，与桩身混凝土抗拉强度无关，D正确。",
        "index": 14
    },
    {
        "type": 0,
        "id": 0,
        "name": "单选题",
        "content": "（单选题）挡墙甲、乙的墙背分别为俯斜和仰斜，关于挡墙所受主动土压力的大小，下列哪个选项的说法是正确的?\r\n",
        "answer": [
            {
                "name": "A",
                "content": "挡墙甲所受主动土压力大于挡墙乙的\r",
                "isanswer": true
            },
            {
                "name": "B",
                "content": "挡墙乙所受主动土压力大于挡墙甲的\r",
                "isanswer": false
            },
            {
                "name": "C",
                "content": "不确定，需看土的强度参数\r",
                "isanswer": false
            },
            {
                "name": "D",
                "content": "如俯斜、仰斜角度的数值大小相同，则两墙所受主动土压力相等\r",
                "isanswer": false
            }
        ],
        "detail": "\r\n【解析】主动土压力与墙背形式有关，也有墙后填土的强度参数有关，在相同土的强度参数情况下，作用在俯斜墙背的土体重量更多，所受的土压力更大。",
        "index": 15
    },
    {
        "type": 0,
        "id": 0,
        "name": "单选题",
        "content": "（单选题）甲、乙两斜坡几何尺寸相同，甲在干燥环境中，乙完全处于静水中，关于其稳定性系数的大小，下列哪个选项的说法是正确的?(水位上下无黏性土的内摩擦角一致)\r\n",
        "answer": [
            {
                "name": "A",
                "content": "甲斜坡的稳定性系数大于乙斜坡的\r",
                "isanswer": false
            },
            {
                "name": "B",
                "content": "两者的稳定性系数相等\r",
                "isanswer": true
            },
            {
                "name": "C",
                "content": "乙斜坡的稳定性系数大于甲斜坡的\r",
                "isanswer": false
            },
            {
                "name": "D",
                "content": "不确定，需看坡高\r",
                "isanswer": false
            }
        ],
        "detail": "\r\n【解析】砂土边坡的稳定系数公式Fs=tanφ/tanα，Fs仅与坡角和砂土的内摩擦角有关，砂土在干燥和水下的内摩擦角基本相同，故安全系数Fs基本上是相同的。如为黏性土则和坡高相关。",
        "index": 16
    },
    {
        "type": 0,
        "id": 0,
        "name": "单选题",
        "content": "（单选题）根据《公路路基设计规范》(JTG D30-2015)，关于路基排水，下列哪个选项的说法是正确的?\r\n",
        "answer": [
            {
                "name": "A",
                "content": "边沟沟底纵坡应大于路线纵坡，困难情况下可适当增加纵坡\r",
                "isanswer": false
            },
            {
                "name": "B",
                "content": "路堑边坡截水沟应设置在坡口5m以外，岩坡面顺接至路堑边沟\r",
                "isanswer": false
            },
            {
                "name": "C",
                "content": "暗沟沟底纵坡不宜小于0.5%，出水口应与地表水排水沟顺接\r",
                "isanswer": false
            },
            {
                "name": "D",
                "content": "仰斜式排水孔的仰角不宜小于6°，水流宜引入路堑边沟\r",
                "isanswer": true
            }
        ],
        "detail": "\r\n【解析】根据《公路路基设计规范》第4.2.4条第2款，边坡沟底纵坡宜与路线纵坡一致，并不宜小于0.3%，A错误；第4.2.5条第3款，截水沟的水流应排至路界之外，不宜引入路堑边沟，B错误；第4.3.4条第2款，暗沟、暗管沟底的纵坡不宜小于1.0%，出水口应加大纵坡，并应高出地表排水沟常水位0.2m以上，C错误；第4.3.6条第2款，仰斜式排水孔的仰角不宜小于6°，排水孔的出水一般是引入路堑边沟的，D正确。",
        "index": 17
    },
    {
        "type": 0,
        "id": 0,
        "name": "单选题",
        "content": "（单选题）安全等级为二级的边坡加固工程中，下列哪个选项的监测项目属于选测项?\r\n",
        "answer": [
            {
                "name": "A",
                "content": "坡顶水平位移与垂直位移 ",
                "isanswer": false
            },
            {
                "name": "B",
                "content": "坡顶建筑物、地下管线变形\r",
                "isanswer": false
            },
            {
                "name": "C",
                "content": "锚杆拉力 ",
                "isanswer": false
            },
            {
                "name": "D",
                "content": "地下水、渗水与降雨关系\r",
                "isanswer": true
            }
        ],
        "detail": "\r\n【解析】根据《建筑边坡工程鉴定与加固技术规范》(GB 50843-2013)表9.2.3，坡顶水平位移与垂直位移、地表裂缝、坡顶建筑物、地下管线变形、锚杆拉力为应测项，二级边坡地下水、渗水与降雨关系为选测项，D正确。本题为边坡加固工程，非一般边坡工程，一般边坡工程根据《建筑边坡工程技术规范》表19.1.3，二级边坡锚杆拉力也为选测项，注意题干关键词，选择正确的规范答题才能答对。",
        "index": 18
    },
    {
        "type": 0,
        "id": 0,
        "name": "单选题",
        "content": "（单选题）某透水路堤土质边坡，当临水面高水位快速下降后，则下列哪个选项是正确的?\r\n",
        "answer": [
            {
                "name": "A",
                "content": "临水面边坡渗透力减小 ",
                "isanswer": false
            },
            {
                "name": "B",
                "content": "临水面边坡抗滑力不变\r",
                "isanswer": false
            },
            {
                "name": "C",
                "content": "背水面边坡滑动力减小 ",
                "isanswer": true
            },
            {
                "name": "D",
                "content": "背水面边坡抗滑力减小\r",
                "isanswer": false
            }
        ],
        "detail": "\r\n【解析】水位快速下降后，迎水坡水向外渗流，渗透力增加滑动力，减少抗滑力，安全系数降低；下游背水面，浸润线降低，渗透力减小，与高水位相比，抗滑力增加，滑动力减小，安全系数提高。",
        "index": 19
    },
    {
        "type": 0,
        "id": 0,
        "name": "单选题",
        "content": "（单选题）砌筑材料相同的两个挡土墙高度分别是6m和4m，无地下水，墙背直立光滑，墙后水平回填同样砂土，则对墙底的倾覆力矩M1和M2的比值最接近下列哪个选项?\r\n",
        "answer": [
            {
                "name": "A",
                "content": "1.50 ",
                "isanswer": false
            },
            {
                "name": "B",
                "content": "2.25\r",
                "isanswer": false
            },
            {
                "name": "C",
                "content": "3.37 ",
                "isanswer": true
            },
            {
                "name": "D",
                "content": "5.06\r",
                "isanswer": false
            }
        ],
        "detail": "\r\n【解析】根据土力学，题目条件符合朗肯土压力理论，对于无黏性土，，土压力三角形分布，倾覆力臂大小L=h/3，则倾覆力矩，M1/M2=63/43=3.375。<img src=\"https://gitee.com/yuebulv/picture/raw/master/yantu/20200416040956234.png\">",
        "index": 20
    },
    {
        "type": 0,
        "id": 0,
        "name": "单选题",
        "content": "（单选题）下列关于重力式挡土墙压力的说法中哪个选项是正确的?\r\n",
        "answer": [
            {
                "name": "A",
                "content": "当墙背与土体的摩擦角增加时，主动土压力减小，被动土压力也减小\r",
                "isanswer": false
            },
            {
                "name": "B",
                "content": "当土的重度增加时，主动土压力增加，被动土压力减小\r",
                "isanswer": false
            },
            {
                "name": "C",
                "content": "当内摩擦角增加时，主动土压力增加，被动土压力减小\r",
                "isanswer": false
            },
            {
                "name": "D",
                "content": "当黏聚力增加时，主动土压力减小，被动土压力增加",
                "isanswer": true
            }
        ],
        "detail": "<img src=\"https://gitee.com/yuebulv/picture/raw/master/yantu/20210404110907193.png\">",
        "index": 21
    },
    {
        "type": 0,
        "id": 0,
        "name": "单选题",
        "content": "（单选题）建筑边坡扶壁式挡土墙构造设计，下列哪个选项是错误的?\r\n",
        "answer": [
            {
                "name": "A",
                "content": "扶壁式挡墙的沉降缝不宜设置在不同结构单元交接处\r",
                "isanswer": true
            },
            {
                "name": "B",
                "content": "当挡墙纵向坡度较大时，在保证地基承载力的前提下可设计成台阶形\r",
                "isanswer": false
            },
            {
                "name": "C",
                "content": "当挡墙基础稳定受滑动控制时，宜在墙底下设防滑键\r",
                "isanswer": false
            },
            {
                "name": "D",
                "content": "当地基为软土时，可采用复合地基处理措施\r",
                "isanswer": false
            }
        ],
        "detail": "\r\n【解析】根据《建筑边坡工程技术规范》(GB 50330-2013)第12.3.9条，宜在不同结构单元处和地层形状变化处设置沉降缝，A错误；第12.3.6条，B正确；第12.3.5条，C正确；第12.3.7条，D正确。",
        "index": 22
    },
    {
        "type": 0,
        "id": 0,
        "name": "单选题",
        "content": "（单选题）下列哪个选项不属于红黏土的主要矿物成分?\r\n",
        "answer": [
            {
                "name": "A",
                "content": "高岭石 ",
                "isanswer": false
            },
            {
                "name": "B",
                "content": "伊利石\r",
                "isanswer": false
            },
            {
                "name": "C",
                "content": "蒙脱石 ",
                "isanswer": true
            },
            {
                "name": "D",
                "content": "绿泥石\r",
                "isanswer": false
            }
        ],
        "detail": "\r\n【解析】根据《工程地质手册》(第五版)P525，红黏土的矿物成分主要为高岭石、伊利石和绿泥石，膨胀土的主要矿物成分为蒙脱石和伊利石，C错误。",
        "index": 23
    },
    {
        "type": 0,
        "id": 0,
        "name": "单选题",
        "content": "（单选题）下列关于我国盐渍土的说法哪个选项是错误的?\r\n",
        "answer": [
            {
                "name": "A",
                "content": "盐渍土中各种盐类，按其在20°水中的溶解度分为易、中、难溶盐三类\r",
                "isanswer": false
            },
            {
                "name": "B",
                "content": "盐渍土测定天然状态下的比重时，用中性液体的比重瓶法\r",
                "isanswer": false
            },
            {
                "name": "C",
                "content": "当盐胀系数和硫酸钠含量两个指标判断的盐胀性不一致时，应以硫酸钠含量为主\r",
                "isanswer": false
            },
            {
                "name": "D",
                "content": "盐渍土的强度指标与含盐量无关\r",
                "isanswer": true
            }
        ],
        "detail": "\r\n【解析】根据《盐渍土地区建筑技术规范》(GB/T 50942-2014)术语与符号第2.1.11~2.1.13条，A正确；附录A第A.0.2条，测定天然状态下的比重用中性液体的比重瓶法，测定浸水淋滤后比重用蒸馏水的比重瓶法测定，B正确；表4.3.4注释，C正确；根据《工程地质手册》(第五版)P595，盐渍土的含盐量对抗剪强度影响较大，D错误。",
        "index": 24
    },
    {
        "type": 0,
        "id": 0,
        "name": "单选题",
        "content": "（单选题）膨胀土地区某挡土墙高度为2.8m，挡墙设计时，破裂面上的抗剪强度指标应采用下列哪个选项的强度指标?\r\n",
        "answer": [
            {
                "name": "A",
                "content": "固结快剪 ",
                "isanswer": false
            },
            {
                "name": "B",
                "content": "饱和状态下的快剪\r",
                "isanswer": true
            },
            {
                "name": "C",
                "content": "直剪慢剪 ",
                "isanswer": false
            },
            {
                "name": "D",
                "content": "反复直剪\r",
                "isanswer": false
            }
        ],
        "detail": "\r\n【解析】根据《膨胀土地区建筑技术规范》(GB 50112-2013)第5.4.4条，高度不大于3m的挡土墙，主动土压力宜采用楔体试算法确定。破裂面上的抗剪强度指标应采用饱和快剪强度指标。",
        "index": 25
    },
    {
        "type": 0,
        "id": 0,
        "name": "单选题",
        "content": "（单选题）某个不稳定斜坡中发育一层倾向与斜坡倾向一致，且倾角小于斜坡坡角的软弱夹层，拟对此夹层进行现场直剪试验，试问，试体上推力方向为下列哪个选项?\r\n",
        "answer": [
            {
                "name": "A",
                "content": "与软弱夹层走向一致 ",
                "isanswer": false
            },
            {
                "name": "B",
                "content": "与软弱夹层倾斜方向一致\r",
                "isanswer": true
            },
            {
                "name": "C",
                "content": "与斜坡倾向相反 ",
                "isanswer": false
            },
            {
                "name": "D",
                "content": "与斜坡走向一致\r",
                "isanswer": false
            }
        ],
        "detail": "\r\n【解析】当软弱夹层与斜坡倾向一致，且倾角小于斜坡坡角时，其最不利方向及为软弱夹层倾斜方向，现场直剪试验时推力方向应与其一致，和2019年案例真题上午第4题和第17题考点一致，华山论剑群发明的从当年专业知识题中找当年案例考点进行预测，成功预测到案例可能出现场直剪试验。",
        "index": 26
    },
    {
        "type": 0,
        "id": 0,
        "name": "单选题",
        "content": "（单选题）某总含水量34%的多年冻土为粉土，该冻土的类型为下列哪个选项?\r\n",
        "answer": [
            {
                "name": "A",
                "content": "饱冰冻土 ",
                "isanswer": true
            },
            {
                "name": "B",
                "content": "富冰冻土\r",
                "isanswer": false
            },
            {
                "name": "C",
                "content": "多冰冻土 ",
                "isanswer": false
            },
            {
                "name": "D",
                "content": "少冰冻土\r",
                "isanswer": false
            }
        ],
        "detail": "\r\n【解析】根据《岩土工程勘察规范》(GB50021-2001)(2009年版)表6.6.2多年冻土的融沉性分类，粉土w0≥32%时，冻土类型为饱冰冻土。",
        "index": 27
    },
    {
        "type": 0,
        "id": 0,
        "name": "单选题",
        "content": "（单选题）采用传递系数法计算滑坡推力时，下列哪个选项是错误的？\r\n",
        "answer": [
            {
                "name": "A",
                "content": "应选择平行于滑动方向的，具有代表性的断面计算，一般不少于2~3个断面，且应有一个主断面\r",
                "isanswer": false
            },
            {
                "name": "B",
                "content": "滑坡推力作用点可取在滑体厚度的二分之一处\r",
                "isanswer": false
            },
            {
                "name": "C",
                "content": "当滑坡具有多层滑动面（带）时，应取最深的滑动面（带）的抗剪强度\r",
                "isanswer": true
            },
            {
                "name": "D",
                "content": "应采用试验和反算，并结合当地经验，合理地确定滑动面（带）的抗剪强度\r",
                "isanswer": false
            }
        ],
        "detail": "\r\n【解析】根据《建筑地基基础设计规范》(GB 50007-2011)第6.4.3条，第2款，A正确；第4款，B正确；第1款，当滑坡具有多层滑动面（带）时，可取推力最大的滑动面（带）确定滑坡推力，C错误；第6款，D正确。本考点历年真题多次出现，应快速作答。",
        "index": 28
    },
    {
        "type": 0,
        "id": 0,
        "name": "单选题",
        "content": "（单选题）关于采空区地表移动盆地的特征，下列哪个说法是错误的?\r\n",
        "answer": [
            {
                "name": "A",
                "content": "地表移动盆地的范围均比采空区面积大得多\r",
                "isanswer": false
            },
            {
                "name": "B",
                "content": "地表移动盆地的形状总是与采空区对称\r",
                "isanswer": true
            },
            {
                "name": "C",
                "content": "移动盆地中间区地表下沉最大\r",
                "isanswer": false
            },
            {
                "name": "D",
                "content": "移动盆地内边缘区产生压缩变形，外边缘区产生拉伸变形\r",
                "isanswer": false
            }
        ],
        "detail": "\r\n【解析】根据《工程地质手册》(第五版)P695~696，矿层倾角较大时，沿倾向方向，移动盆地与采空区的关系是非对称的，B错误；采空区经常在《工程地质手册》出题，应做好书签。",
        "index": 29
    },
    {
        "type": 0,
        "id": 0,
        "name": "单选题",
        "content": "（单选题）某地覆盖于灰岩之上的厚层红黏土，天然含水率30%，液限51%，塑限25%，在裂隙密集方向上3m长度发现裂隙6条，则该场地红黏土可定性为下列哪个选项?\r\n",
        "answer": [
            {
                "name": "A",
                "content": "坚硬、碎块状 ",
                "isanswer": false
            },
            {
                "name": "B",
                "content": "硬塑、巨块状\r",
                "isanswer": true
            },
            {
                "name": "C",
                "content": "坚硬、巨块状 ",
                "isanswer": false
            },
            {
                "name": "D",
                "content": "硬塑、碎块状\r",
                "isanswer": false
            }
        ],
        "detail": "\r\n【解析】根据《工程地质手册》(第五版)P527～528，或《岩土工程勘察规范》第6.2.2条，，，查表5-2-4，为硬塑；红黏土网状裂隙裂隙2条/m，为较多裂隙，根据表5-2-5，厚层红黏土为巨块状结构。\r\n<img src=\"https://gitee.com/yuebulv/picture/raw/master/yantu/20200416045743426.png\">",
        "index": 30
    },
    {
        "type": 0,
        "id": 0,
        "name": "单选题",
        "content": "（单选题）某溶岩场地面积约2km2，地表调查发现5处直径0.5~0.9m的塌陷坑。场地内钻孔30个，总进尺1000m，钻孔抽水试验测得单位涌水量0.3~0.6L/m·s，则场地岩溶发育等级为下列哪个选项?\r\n",
        "answer": [
            {
                "name": "A",
                "content": "强烈发育 ",
                "isanswer": false
            },
            {
                "name": "B",
                "content": "中等发育\r",
                "isanswer": true
            },
            {
                "name": "C",
                "content": "弱发育 ",
                "isanswer": false
            },
            {
                "name": "D",
                "content": "不发育\r",
                "isanswer": false
            }
        ],
        "detail": "\r\n【解析】根据《工程地质手册》(第五版)P637~638，查表6-2-2，地表岩溶发育密度=5/2=2.5个/km2，单位涌水量0.3~0.6L/m·s，为岩溶中等发育，华山论剑群根据本知识题成功预测专业案例出岩溶发育等级题2019C03。",
        "index": 31
    },
    {
        "type": 0,
        "id": 0,
        "name": "单选题",
        "content": "（单选题）对于某膨胀土场地的挡土结构，下列有关设计和构造措施哪个选项是正确的?\r\n",
        "answer": [
            {
                "name": "A",
                "content": "挡土结构基础埋深应经稳定性验算确定，基础埋深应在滑动面以下且不应小于1.0m\r",
                "isanswer": false
            },
            {
                "name": "B",
                "content": "墙背滤水层的宽度不应小于300mm\r",
                "isanswer": false
            },
            {
                "name": "C",
                "content": "高度不大于3m的挡土墙，在采取规定的防排水和构造措施情况下，土压力计算时可不计膨胀力的作用\r",
                "isanswer": true
            },
            {
                "name": "D",
                "content": "挡土墙每隔12m~15m应设置变形缝\r",
                "isanswer": false
            }
        ],
        "detail": "\r\n【解析】根据《膨胀土地区建筑技术规范》(GB 50112-2013)第5.4.2条第2款，挡土结构基础埋深应由稳定性验算确定，并应埋置在滑动面以下且不应小于1.5m，A错误；第5.4.3条第1款，墙背滤水层的宽度不应小于500mm，B错误；第3款，挡土墙每隔6m～10m和转角部位应设置变形缝，D错误；第5.4.4条，高度不大于3m的挡土墙，在采取构造符合本规范5.4.3条规定时，土压力计算时可不计膨胀力的作用，C正确。本题历年真题多次出题。",
        "index": 32
    },
    {
        "type": 0,
        "id": 0,
        "name": "单选题",
        "content": "（单选题）某盐渍土建筑场地，室内试验测得盐渍土的膨胀系数为0.030，硫酸钠含量为1.0%。该盐渍土的盐胀性分类正确选项是哪一个?\r\n",
        "answer": [
            {
                "name": "A",
                "content": "非盐胀性 ",
                "isanswer": false
            },
            {
                "name": "B",
                "content": "弱盐胀性\r",
                "isanswer": true
            },
            {
                "name": "C",
                "content": "中盐胀性 ",
                "isanswer": false
            },
            {
                "name": "D",
                "content": "强盐胀性\r",
                "isanswer": false
            }
        ],
        "detail": "\r\n【解析】根据《盐渍土地区建筑技术规范》(GB/T 50942-2014)第4.3.4条，δyz=0.03为中盐胀性，Cssn=1.0为弱盐胀性，注意表4.3.4小注，当两个指标不一致，以硫酸钠含量为主，为弱盐胀性。",
        "index": 33
    },
    {
        "type": 0,
        "id": 0,
        "name": "单选题",
        "content": "（单选题）下列关于膨胀土性质和成因表述正确的是哪个选项？\r\n",
        "answer": [
            {
                "name": "A",
                "content": "黏性土的蒙脱石含量和阳离子交换量越大，自由膨胀率越大\r",
                "isanswer": true
            },
            {
                "name": "B",
                "content": "钙蒙脱石和钠蒙脱石含量相同的两种膨胀土，前者比后者具有更大的膨胀潜势\r",
                "isanswer": false
            },
            {
                "name": "C",
                "content": "膨胀土由坡积、残积形成，没有冲积成因的膨胀土\r",
                "isanswer": false
            },
            {
                "name": "D",
                "content": "膨胀土初始含水量与胀后含水量差值越小，膨胀量越大\r",
                "isanswer": false
            }
        ],
        "detail": "\r\n【解析】根据《工程地质手册》(第五版)P553~556，控制膨胀土涨缩势能大小的物质成分主要是土重的蒙脱石的含量、离子交换量以及小于2μm黏粒含量，A正确；根据表5-5-2，蒙脱石钠的活动性为7.2，蒙脱石钙的活动性为1.5，蒙脱石钠具有更大的膨胀潜势，B错误；国内外膨胀土的成因多数属残积型、坡积型，洪积、冲积或其他成因的膨胀土也有，C错误；膨胀土含水量变化，易产生胀缩变形，当初始含水量与胀后含水量愈接近，土的膨胀就小，D错误。",
        "index": 34
    },
    {
        "type": 0,
        "id": 0,
        "name": "单选题",
        "content": "（单选题）根据住房和城乡建设部办公厅关于实施《危险性较大的分部分项工程安全管理规定》有关问题的通知(建办质[2018]31号)的规定，下列哪个选项不属于超过一定规模的危险性较大的分部分项工程范围?\r\n",
        "answer": [
            {
                "name": "A",
                "content": "开挖深度超过5m(含5m)的基坑\r",
                "isanswer": false
            },
            {
                "name": "B",
                "content": "开挖深度15m及以上的人工挖孔桩工程\r",
                "isanswer": true
            },
            {
                "name": "C",
                "content": "搭设高度50m及以上的落地式钢管脚手架工程\r",
                "isanswer": false
            },
            {
                "name": "D",
                "content": "搭设高度8m及以上的混凝土模板支撑工程\r",
                "isanswer": false
            }
        ],
        "detail": "\r\n【解析】根据《危险性较大的分部分项工程安全管理规定》有关问题的通知（建办质[2018]31号）附件1《危险性较大分部分项工程告知书》。本题考点超出2019年考试大纲的目录，为建造师常考知识点，人工挖孔桩工程开挖深度16m及以上的人工挖孔桩工程，属于超过一定规模的危险性较大的分部分项工程，B错误。",
        "index": 35
    },
    {
        "type": 0,
        "id": 0,
        "name": "单选题",
        "content": "（单选题）下列哪个选项不符合规定?\r\n",
        "answer": [
            {
                "name": "A",
                "content": "建设单位应当向施工单位提供供水、排水、供电、供气、通信、广播电视等地下管线资料，气象和水文观测资料，相邻建筑物和构筑物、地下工程的有关资料，并保证资料的真实、准确、完整\r",
                "isanswer": false
            },
            {
                "name": "B",
                "content": "勘察单位在勘察作业时，应当严格执行操作规程，采取措施保证各类管线、设施和周边建筑物、构筑物的安全\r",
                "isanswer": false
            },
            {
                "name": "C",
                "content": "施工单位应当设立安全生产管理机构，配备专职安全生产管理人员。施工单位的项目负责人负责对安全生产进行现场监督检查\r",
                "isanswer": true
            },
            {
                "name": "D",
                "content": "施工单位项目负责人应当由取得相应职业资格的人员担任，对建设工程项目的安全施工负责\r",
                "isanswer": false
            }
        ],
        "detail": "\r\n【解析】根据《建设工程安全生产管理条例》第六条，A正确；第十二条，B正确；第二十三条，专职安全生产管理人员负责对安全生产进行现场监督检查，C不符合规定；第二十一条，D正确。",
        "index": 36
    },
    {
        "type": 0,
        "id": 0,
        "name": "单选题",
        "content": "（单选题）下列说法中哪个选项是错误的?\r\n",
        "answer": [
            {
                "name": "A",
                "content": "生产经营单位必须遵守有关安全生产的法律、法规，建立健全安全生产责任制和安全生产规章制度，改善安全生产条件，确保生产安全\r",
                "isanswer": false
            },
            {
                "name": "B",
                "content": "生产经营单位的主要负责人对本单位的安全生产工作全面负责\r",
                "isanswer": false
            },
            {
                "name": "C",
                "content": "生产经营单位与从业人员订立协议，可免除或减轻其对从业人员因生产安全事故伤亡依法应承担的责任\r",
                "isanswer": true
            },
            {
                "name": "D",
                "content": "生产经营单位的从业人员有依法获得安全生产保障的权利，并应当依法履行安全生产方面的义务\r",
                "isanswer": false
            }
        ],
        "detail": "\r\n【解析】根据《中华人民共和国安全生产法》第三条，A正确；第五条，B正确；第四十九条，生产经营单位不得以任何形式与从业人员订立协议，免除或者减轻其对从业人员因生产安全事故伤亡依法应承担的责任，C错误；第六条，D正确。",
        "index": 37
    },
    {
        "type": 0,
        "id": 0,
        "name": "单选题",
        "content": "（单选题）两个以上生产经营单位在同一作业区域内进行生产经营活动，可能危及对方生产安全的，下列说法哪个选项是错误的?\r\n",
        "answer": [
            {
                "name": "A",
                "content": "双方应当签订安全生产管理协议\r",
                "isanswer": false
            },
            {
                "name": "B",
                "content": "明确各自的安全生产管理职责和应当采取的安全措施\r",
                "isanswer": false
            },
            {
                "name": "C",
                "content": "指定专职安全生产管理人员进行安全检查与协调\r",
                "isanswer": false
            },
            {
                "name": "D",
                "content": "一方人员发现另外一方作业区域内有安全生产事故隐患或者其他不安全因素，无需向现场安全生产管理人员或者本单位负责人报告\r",
                "isanswer": true
            }
        ],
        "detail": "\r\n【解析】根据《中华人民共和国安全生产法》第四十五条，两个以上生产经营单位在同一作业区域内进行生产经营活动，可能危及对方生产安全的，应当签订安全生产管理协议，明确各自的安全生产管理职责和应当采取的安全措施，并指定专职安全生产管理人员进行安全检查与协调，A、B、C正确，D选项明显不合理，错误。",
        "index": 38
    },
    {
        "type": 0,
        "id": 0,
        "name": "单选题",
        "content": "（单选题）关于施工单位现场安全措施，下列说法哪个选项是错误的?\r\n",
        "answer": [
            {
                "name": "A",
                "content": "施工单位应当将施工现场的办公、生活区与作业区分开设置，并保持安全距离\r",
                "isanswer": false
            },
            {
                "name": "B",
                "content": "办公、生活区的选址应当符合安全性要求\r",
                "isanswer": false
            },
            {
                "name": "C",
                "content": "职工的膳食、饮水、休息场所等应当符合卫生标准\r",
                "isanswer": false
            },
            {
                "name": "D",
                "content": "施工单位在保证安全情况下，可在未竣工的建筑物内设置员工集体宿舍\r",
                "isanswer": true
            }
        ],
        "detail": "\r\n【解析】根据《建设工程安全生产管理条例》第二十九条，施工单位应当将施工现场的办公、生活区与作业区分开设置，并保持安全距离；办公、生活区的选址应当符合安全性要求。职工的膳食、饮水、休息场所等应当符合卫生标准。施工单位不得在尚未竣工的建筑物内设置员工集体宿舍，A、B、C正确，D错误。",
        "index": 39
    },
    {
        "type": 0,
        "id": 0,
        "name": "单选题",
        "content": "（单选题）违反的规定，建设单位有下列行为之一的，责令限期改正，处20万元以上50万元以下的罚款，下列选项中哪个行为不适用该处罚规定?\r\n",
        "answer": [
            {
                "name": "A",
                "content": "未按照法律、法规和工程建设强制性标准进行勘察、设计\r",
                "isanswer": true
            },
            {
                "name": "B",
                "content": "对勘察、设计、施工、工程监理等单位提出不符合安全生产法律、法规和强制性标准固定的要求的\r",
                "isanswer": false
            },
            {
                "name": "C",
                "content": "要求施工单位压缩合同约定的工期的\r",
                "isanswer": false
            },
            {
                "name": "D",
                "content": "将拆除工程发包给不具有相应资质登记的施工单位的\r",
                "isanswer": false
            }
        ],
        "detail": "\r\n【解析】根据《建设工程安全生产管理条例》第五十五条，建设单位有下列行为之一的，责令限期改正，处20万元以上50万元以下的罚款；造成重大安全事故，构成犯罪的，对直接责任人员，依照刑法有关规定追究刑事责任；造成损失的，依法承担赔偿责任：(一)对勘察、设计、施工、工程监理等单位提出不符合安全生产法律、法规和强制性标准规定的要求的；(二)要求施工单位压缩合同约定的工期的；(三)将拆除工程发包给不具有相应资质等级的施工单位的，B、C、D正确；第五十六条，未按照法律、法规和工程建设强制性标准进行勘察、设计的，处10万元以上30万元以下的罚款，A错误。对应罚款类法规题目，很难记住，华山版法规第二个罚款总结表可直接查询定位20万~50万罚款的相关规定P117。",
        "index": 40
    },
    {
        "type": 1,
        "id": 0,
        "name": "多选题",
        "content": "（多选题）理论上关于土的压缩模量与变形模量，下列说法正确的是哪些选项?\r\n",
        "answer": [
            {
                "name": "A",
                "content": "压缩模量为完全侧限模量 ",
                "isanswer": true
            },
            {
                "name": "B",
                "content": "变形模量为无侧限模量\r",
                "isanswer": false
            },
            {
                "name": "C",
                "content": "压缩模量大于变形模量 ",
                "isanswer": true
            },
            {
                "name": "D",
                "content": "压缩模量小于变形模量\r",
                "isanswer": false
            }
        ],
        "detail": "\r\n【解析】根据《土力学》(清华大学，第二版，李广信)P127~133，压缩模量Es属于完全侧限模量，变形模量E属于部分侧限模量，侧限模量E=βEs，β=1-2ν2/(1+ν)，β＜1，压缩模量大于变形模量。土力学的基本知识，应达到闭卷快速作答。",
        "index": 41
    },
    {
        "type": 1,
        "id": 0,
        "name": "多选题",
        "content": "（多选题）下列关于软弱下卧层承载力验算说法正确的是哪些选项?\r\n",
        "answer": [
            {
                "name": "A",
                "content": "用荷载准永久组合计算基础底面处的附加压力\r",
                "isanswer": false
            },
            {
                "name": "B",
                "content": "用荷载标准组合计算软弱下卧层顶面处的附加压力\r",
                "isanswer": true
            },
            {
                "name": "C",
                "content": "压力扩散角是压力扩散线与水平线的夹角\r",
                "isanswer": false
            },
            {
                "name": "D",
                "content": "软弱下卧层顶面处的地基承载力特征值需要进行深度修正\r",
                "isanswer": true
            }
        ],
        "detail": "\r\n【解析】根据《建筑地基基础设计规范》(GB 50007-2011)第5.2.7条第2款，计算基础底面处和弱下卧层顶面处均采用标准组合，A错误，B正确；θ为地基压力扩散线与竖直线的夹角，C错误；第一款，faz为经过深度修正后的地基承载特征值，D正确；本题为专业案例必考的考点，应做到熟练闭卷快速作答。",
        "index": 42
    },
    {
        "type": 1,
        "id": 0,
        "name": "多选题",
        "content": "（多选题）基于地基-基础共同作用原理，计算内力和变形时，必须满足下列哪些条件?\r\n",
        "answer": [
            {
                "name": "A",
                "content": "静力平衡条件 ",
                "isanswer": true
            },
            {
                "name": "B",
                "content": "土体破裂准则\r",
                "isanswer": false
            },
            {
                "name": "C",
                "content": "变形协调作用 ",
                "isanswer": true
            },
            {
                "name": "D",
                "content": "极限平衡条件\r",
                "isanswer": false
            }
        ],
        "detail": "\r\n【解析】根据《北京地区建筑地基基础勘察设计规范》(DBJ11-501-2016)第2.1.10协同作用分析条案，根据静力平衡和变形协调条件，采用经过验证的地基土本构模型和基础与上部结构模型，建立和求解反映整个系统相互作用的方程，用以计算变形和内力，A、C正确。土体破裂准则和极限平衡条件涉及土体的强度问题，和内力和变形无关，B、D错误。",
        "index": 43
    },
    {
        "type": 1,
        "id": 0,
        "name": "多选题",
        "content": "（多选题）计算建筑物地基变形时，不能忽略下列哪些荷载？\r\n",
        "answer": [
            {
                "name": "A",
                "content": "家具荷载 ",
                "isanswer": true
            },
            {
                "name": "B",
                "content": "风荷载\r",
                "isanswer": false
            },
            {
                "name": "C",
                "content": "地震荷载 ",
                "isanswer": false
            },
            {
                "name": "D",
                "content": "装修荷载\r",
                "isanswer": true
            }
        ],
        "detail": "\r\n【解析】根据《建筑地基基础设计规范》(GB 50007-2011)第3.0.5条第2款，计算地基变形时，传至基础底面上的作用效应应按正常使用极限状态下作用的准永久组合，不应计入风荷载和地震作用，故不选B和C；根据《建筑结构荷载规范》(GB 50009-2012)第4.0.1条，家具荷载和装修荷载属于永久荷载，不能忽略。",
        "index": 44
    },
    {
        "type": 1,
        "id": 0,
        "name": "多选题",
        "content": "（多选题）下列四种建筑工程设计条件中，哪些选项的建筑需要进行变形验算?\r\n",
        "answer": [
            {
                "name": "A",
                "content": "7层住宅楼，体型简单，荷载分布均匀，地基承载力特征值210kPa，土层坡度12%\r",
                "isanswer": true
            },
            {
                "name": "B",
                "content": "防疫站化验楼，砌体结构，5层，地基承载力特征值150kPa，土层坡度3%\r",
                "isanswer": true
            },
            {
                "name": "C",
                "content": "5层框架办公楼，地基承载力特征值100kPa，土层坡度7%\r",
                "isanswer": false
            },
            {
                "name": "D",
                "content": "单层排架厂房，地基承载力特征值160kPa，土体坡度12%，陡度28m，吊车25t\r",
                "isanswer": true
            }
        ],
        "detail": "\r\n【解析】根据《建筑地基基础设计规范》(GB 50007-2011)表3.0.1、3.0.2和表3.0.3，A选项，坡度＞10%，需要变形验算；B选项，防疫站化验楼非丙类建筑，需要进行变形验算；C选项，满足100kPa≤fak＜130kPa，土层坡度≤10%，层数≤5，且属于丙级的建筑物，可不作地基变形验算的设计等级；D选项，坡度＞10%，需要变形验算。",
        "index": 45
    },
    {
        "type": 1,
        "id": 0,
        "name": "多选题",
        "content": "（多选题）某钻孔灌注桩采用泵吸反循环成孔，为提高钻进效率，采取下列哪些措施是有效的?\r\n",
        "answer": [
            {
                "name": "A",
                "content": "控制上返冲洗液中合适的钻屑含量\r",
                "isanswer": true
            },
            {
                "name": "B",
                "content": "选用合理的钻杆内径\r",
                "isanswer": true
            },
            {
                "name": "C",
                "content": "控制钻杆在孔内的沉落速度\r",
                "isanswer": false
            },
            {
                "name": "D",
                "content": "控制上返冲洗液中钻屑最大粒径\r",
                "isanswer": true
            }
        ],
        "detail": "\r\n【解析】反循环是钻杆吸出夹带钻碴的循环泥浆，并孔顶补充泥浆以保持孔内液面，从而保证孔壁的稳定性。反循环可大大减少重复碾磨钻碴的无效劳动，可使钻进效率大幅度提高。钻进中应控制上返冲洗液中岩屑含量不大于5％～8％，A正确；要选择合理的钻杆内径，泵体内的液体通道直径应大于钻杆内径，B正确；钻头上应装设吸水喉管，控制上返冲洗液中钻屑最大粒径，喉管的内径应小于钻杆内径5mm～10mm，喉管安装部位距钻头底部不应小于150mm～200mm，防止堵塞钻杆，D正确；钻杆给进太快，会使得钻头堵塞或者管路堵塞，不是钻杆的沉落速度，C错误。本题难度较大，大纲规范上无相关内容，考场建议快速作答，无论对错。",
        "index": 46
    },
    {
        "type": 1,
        "id": 0,
        "name": "多选题",
        "content": "（多选题）采用反循环回转钻成孔工艺，遇坚硬基岩时，采取下列哪些钻进措施是合理的?\r\n",
        "answer": [
            {
                "name": "A",
                "content": "高钻压钻进 ",
                "isanswer": true
            },
            {
                "name": "B",
                "content": "高转速钻进\r",
                "isanswer": false
            },
            {
                "name": "C",
                "content": "调大泥浆比重 ",
                "isanswer": false
            },
            {
                "name": "D",
                "content": "改换球形刃碎岩钻头\r",
                "isanswer": true
            }
        ],
        "detail": "\r\n【解析】低钻速、高钻压适用于坚硬地层，钻速过高时，由于切削齿与地层接触时间太短，会出现无进尺和钻速太慢的现象，加大钻压有利于切削齿和地层的接触，提高钻进速度，A正确，B错误；调大泥浆比重只会提高排渣能力，对钻进基本无影响，C错误；球形刃碎岩钻头具有动、静载相结合的碎岩方式，碎岩效率较高，适宜钻进坚硬岩层，D正确。本题需要一定的桩基施工经验，可快速作答，不必纠结浪费时间。",
        "index": 47
    },
    {
        "type": 1,
        "id": 0,
        "name": "多选题",
        "content": "（多选题）近年来，铁路建设中采用挖井基础形式，下列关于铁路挖井基础和沉井基础特点的说法，哪些是正确的?\r\n",
        "answer": [
            {
                "name": "A",
                "content": "沉井基础和挖井基础是施工过程中都需要利用井身混凝土自重作用克服井壁与土的摩阻力和刃脚底面上的阻力\r",
                "isanswer": false
            },
            {
                "name": "B",
                "content": "沉井基础施工是垂直下沉，不需要放坡，挖井基础可根据场地条件放坡施工\r",
                "isanswer": false
            },
            {
                "name": "C",
                "content": "沉井基础适用于水下或地下水丰富的场地和地层条件，挖井基础适用于无地下水的场地和地层条件\r",
                "isanswer": true
            },
            {
                "name": "D",
                "content": "沉井基础和挖井基础设计时，井壁与土体之间的摩阻力都可根据沉井和挖井地点土层己有测试资料和参考以往类似沉井和挖井设计中的侧摩阻力\r",
                "isanswer": true
            }
        ],
        "detail": "\r\n【解析】根据《铁路桥涵地基和基础设计规范》(TB 10093-2017)第8.1.7条，挖井基础采用现浇混凝土灌注，不需要利用井身自重克服阻力，A错误；根据第8.1.4条，挖井基础施工应垂直开挖，护壁及时跟进，不应放坡开挖，B错误；第7.1.1条和8.1.1条，C正确；第7.1.2条和第8.2.3条，D正确。",
        "index": 48
    },
    {
        "type": 1,
        "id": 0,
        "name": "多选题",
        "content": "（多选题）某抗拔预应力管桩位于中腐蚀性场地，环境类别为二（a），根据《建筑桩基技术规范》(JGJ 94-2008)，下列说法正确的是哪些选项?\r\n",
        "answer": [
            {
                "name": "A",
                "content": "桩身裂缝控制等级为一级\r",
                "isanswer": true
            },
            {
                "name": "B",
                "content": "桩身裂缝控制等级为二级\r",
                "isanswer": false
            },
            {
                "name": "C",
                "content": "在荷载效应标准组合下，桩身最大裂缝宽度为0\r",
                "isanswer": true
            },
            {
                "name": "D",
                "content": "在荷载效应准永久组合下，桩身最大裂缝宽度为0\r",
                "isanswer": true
            }
        ],
        "detail": "\r\n【解析】根据《建筑桩基技术规范》(JGJ 94-2008)表3.5.3，查表二（a）环境类别时，预应力混凝土桩的裂缝控制等级为二级，最大裂缝宽度为0；根据注1：水、土为强、中腐蚀性时，抗拔桩裂缝控制等级应提高一级，故桩身裂缝控制等级为一级，A正确；根据5.8.8条，一级裂缝控制等级预应力混凝土基桩，在荷载效应标准组合下混凝土不应产生拉应力，C正确；准永久组合下准永久组合下正截面法向应力≤扣除全部应力损失后桩身混凝土的预应力，即裂缝宽度为0，D正确。\r\n",
        "index": 49
    },
    {
        "type": 1,
        "id": 0,
        "name": "多选题",
        "content": "（多选题）泥浆护壁钻孔灌注桩施工时，关于护筒主要作用的说法哪些是正确的?\r\n",
        "answer": [
            {
                "name": "A",
                "content": "减少泥浆比重 ",
                "isanswer": false
            },
            {
                "name": "B",
                "content": "防止孔口塌孔\r",
                "isanswer": true
            },
            {
                "name": "C",
                "content": "提高桩头承载力 ",
                "isanswer": false
            },
            {
                "name": "D",
                "content": "控制桩位施工误差\r",
                "isanswer": true
            }
        ],
        "detail": "\r\n【解析】护筒的主要作用是固定桩位，引导钻孔方向，隔离地表水免其流入井孔，保护孔口不坍塌，并保证孔内泥浆水位高出地下水位或施工水位一定高度，形成静水压力，以保护孔壁免于坍塌，故B、D正确；护筒的埋设深度一般不大，不能因为护筒就减小泥浆比重，A错误；桩头承载力取决于桩头的结构强度，与护筒无关，C错误。",
        "index": 50
    },
    {
        "type": 1,
        "id": 0,
        "name": "多选题",
        "content": "（多选题）一柱一桩条件下，关于事故桩的处理方法，下列哪些选项是合理的?\r\n",
        "answer": [
            {
                "name": "A",
                "content": "破除重打 ",
                "isanswer": true
            },
            {
                "name": "B",
                "content": "在事故桩两侧各补打一根\r",
                "isanswer": true
            },
            {
                "name": "C",
                "content": "在事故桩一侧补打一根 ",
                "isanswer": false
            },
            {
                "name": "D",
                "content": "降低承载力使用\r",
                "isanswer": false
            }
        ],
        "detail": "\r\n【解析】一柱一桩时，对桩的要求非常高，破除重打，破除费用高，但是解决问题最直接的方法，A正确；在事故桩两侧各补打一根，然后做上搭接承台，也可以满足受力的要求，B正确；在事故桩一侧补打一根，改变了柱子的位置，不合理，C错误；降低承载力使用满足不了柱子的要求，D错误。理解类题目，可采用排除法作答。",
        "index": 51
    },
    {
        "type": 1,
        "id": 0,
        "name": "多选题",
        "content": "（多选题）后注浆改善灌注桩承载特性的机理包括以下哪些选项?\r\n",
        "answer": [
            {
                "name": "A",
                "content": "桩身结构强度增大 ",
                "isanswer": false
            },
            {
                "name": "B",
                "content": "桩端沉渣加固强化\r",
                "isanswer": true
            },
            {
                "name": "C",
                "content": "桩侧泥皮加固强化 ",
                "isanswer": true
            },
            {
                "name": "D",
                "content": "桩端平面附加应力减小\r",
                "isanswer": false
            }
        ],
        "detail": "\r\n【解析】根据《建筑桩基技术规范》(JGJ 94-2008)P263~264第5.3.10条文说明，改善的机理包括桩端沉渣和土的加固效应和桩侧你提（泥皮）的加固效应，B、C正确；桩身强度主要取决于桩身混凝土的强度和配筋，和后注浆无关，A错误；桩端平面附加应力取决于承台的受力等，也与后注浆无关，D错误。",
        "index": 52
    },
    {
        "type": 1,
        "id": 0,
        "name": "多选题",
        "content": "（多选题）以下关于坝内水平排水设计哪些选项是正确的?\r\n",
        "answer": [
            {
                "name": "A",
                "content": "排水层中每层料的最小厚度应满足反滤层最小厚度要求\r",
                "isanswer": true
            },
            {
                "name": "B",
                "content": "网状排水带中的横向排水带宽度不应小于0.5m，坡度不宜超过1.0%\r",
                "isanswer": true
            },
            {
                "name": "C",
                "content": "采用排水管对渗流量较大的坝体排水时，管径不得小于0.2m，坡度不大于5%\r",
                "isanswer": true
            },
            {
                "name": "D",
                "content": "对于黏性土或者砂性土均质坝，坝内水平排水设施伸进坝体的极限尺寸，为坝底宽的1/3\r",
                "isanswer": false
            }
        ],
        "detail": "\r\n【解析】根据《碾压式土石坝设计规范》(DL/T 5395-2007）第7.6.8条，A正确；第7.7.9条第2款，B正确；第3款，C正确；第4款，对于均质坝，宜为坝底宽度的1/2，对砂质坝，宜为1/3，D错误。",
        "index": 53
    },
    {
        "type": 1,
        "id": 0,
        "name": "多选题",
        "content": "（多选题）边坡支护结构设计时，下列哪些选项是必须进行的计算或验算?\r\n",
        "answer": [
            {
                "name": "A",
                "content": "支护桩的抗弯承载力计算 ",
                "isanswer": true
            },
            {
                "name": "B",
                "content": "重力式挡墙的地基承载力计算\r",
                "isanswer": true
            },
            {
                "name": "C",
                "content": "边坡变形验算 ",
                "isanswer": false
            },
            {
                "name": "D",
                "content": "支护结构的稳定性验算\r",
                "isanswer": true
            }
        ],
        "detail": "\r\n【解析】根据《建筑边坡工程技术规范》(GB 50330-2013）第3.3.6条第1款，A、B正确，第3款，D正确。根据3.3.7条，对变形有较高要求的边坡工程还应结合当地经验进行变形验算，不是必须验算，C错误。本题为2016B57，真题重现，历年真题应引起重视。",
        "index": 54
    },
    {
        "type": 1,
        "id": 0,
        "name": "多选题",
        "content": "（多选题）关于土坡稳定性的论述中，下列哪些选项是正确的?\r\n",
        "answer": [
            {
                "name": "A",
                "content": "无黏性土坡的稳定性与坡高无关\r",
                "isanswer": true
            },
            {
                "name": "B",
                "content": "黏性土坡稳定性与坡高有关\r",
                "isanswer": true
            },
            {
                "name": "C",
                "content": "所有土坡均可按圆弧滑面整体稳定性分析方法计算\r",
                "isanswer": false
            },
            {
                "name": "D",
                "content": "简单条分法假定不考虑土条之间的作用力\r",
                "isanswer": true
            }
        ],
        "detail": "\r\n【解析】无黏性土K=tanφ/tanα，K仅与内摩擦角和坡角有关，A正确；根据泰勒公式，黏性土坡有极限高度，因此黏性土坡稳定性与坡高有关，B正确；圆弧滑面整体稳定性分析法仅适用φ=0°的均质黏性土，C错误；简单条分法不考虑土条间作用力，D正确。04B54真题重现。",
        "index": 55
    },
    {
        "type": 1,
        "id": 0,
        "name": "多选题",
        "content": "（多选题）工程滑坡防治应针对性地选择一种或者多种有效措施，制定合理的方案。下列哪些措施是正确的?\r\n",
        "answer": [
            {
                "name": "A",
                "content": "采取有效的地表截排水和地下排水措施\r",
                "isanswer": true
            },
            {
                "name": "B",
                "content": "结合滑坡的特性，采取合理的支挡结构\r",
                "isanswer": true
            },
            {
                "name": "C",
                "content": "在滑坡的抗滑段采取刷方减载\r",
                "isanswer": false
            },
            {
                "name": "D",
                "content": "采用加筋土反压及加强反压区地下水引排\r",
                "isanswer": true
            }
        ],
        "detail": "\r\n【解析】根据《《建筑边坡工程技术规范》(GB 50330-2013）第17.2.1条及条文说明，治理措施有：排水、支挡、减载、反压、改良滑带、植被绿化。A、B、D正确；刷方减载应在滑坡的主滑段实施，并应采取措施防止地面水浸入坡体内，严禁在滑坡的抗滑段减载和减载诱发次生地质灾害，C错误。\r\n",
        "index": 56
    },
    {
        "type": 1,
        "id": 0,
        "name": "多选题",
        "content": "（多选题）土质边坡在暴雨期间或过后易发生滑坡，下列哪些选项的因素与暴雨诱发滑坡有关?\r\n",
        "answer": [
            {
                "name": "A",
                "content": "土体基质吸力增加 ",
                "isanswer": false
            },
            {
                "name": "B",
                "content": "坡体内渗透力增大\r",
                "isanswer": true
            },
            {
                "name": "C",
                "content": "土体孔隙水压力升高 ",
                "isanswer": true
            },
            {
                "name": "D",
                "content": "土体抗剪强度降低\r",
                "isanswer": true
            }
        ],
        "detail": "\r\n【解析】土体基质吸力是非饱和土之间作用力，暴雨后的土体是饱和的，A错误；暴雨会在土体内产生顺滑坡方向渗流，产生渗透力，加大了下滑力，B正确；降水流渗入坡体，使得土体饱和，加大孔隙水压力，减小了抗滑力，C正确；暴雨从地表渗入土体，使土体软化，导致土的抗剪强度降低，D正确。",
        "index": 57
    },
    {
        "type": 1,
        "id": 0,
        "name": "多选题",
        "content": "（多选题）下列哪些选项是溶岩强发育的岩溶场地条件?\r\n",
        "answer": [
            {
                "name": "A",
                "content": "地表较多塌陷、漏斗 ",
                "isanswer": true
            },
            {
                "name": "B",
                "content": "溶槽、石芽密布\r",
                "isanswer": true
            },
            {
                "name": "C",
                "content": "地下有暗河 ",
                "isanswer": true
            },
            {
                "name": "D",
                "content": "钻孔见洞率为24%\r",
                "isanswer": false
            }
        ],
        "detail": "\r\n【解析】根据《工程地质手册》(第五版)P637表6-2-1 岩溶发育程度表，强发育的岩溶场地条件，其中钻孔见洞率大于30%，D错误。",
        "index": 58
    },
    {
        "type": 1,
        "id": 0,
        "name": "多选题",
        "content": "（多选题）关于湿陷性黄土地区的地基处理措施，下列哪些选项不符合规定?\r\n",
        "answer": [
            {
                "name": "A",
                "content": "甲、乙类建筑应消除地基的部分湿陷量\r",
                "isanswer": true
            },
            {
                "name": "B",
                "content": "在自重湿陷黄土场地局部处理地基时，其处理范围每边应超出基础底面宽度的1/4\r",
                "isanswer": true
            },
            {
                "name": "C",
                "content": "自重湿陷性黄土场地的乙类建筑，其处理厚度不应小于地基压缩深度的2/3，且下部未处理湿陷性黄土层的湿陷起始压力值不应小于100kPa\r",
                "isanswer": true
            },
            {
                "name": "D",
                "content": "非自重湿陷性黄土场地上的丙类多层建筑，地基湿陷等级为II级，处理厚度不宜小于2m，且下部未处理湿陷性黄土层的湿陷起始压力值不宜小于100kPa\r",
                "isanswer": false
            }
        ],
        "detail": "\r\n【解析】根据《湿陷性黄土地区建筑标准》(GB 50025-2018)6.1.1条第1款、第2款，A错误；6.1.6条第1款，自重湿陷性黄土场地应采用整片处理，B错误；6.1.4条第2款，自重湿陷性黄土场地的乙类建筑，处理深度不应小于基底下湿陷性土层的2/3，且下部未处理湿陷性黄土层的剩余湿陷量不应大于150mm，C错误；根据6.1.5条续表6.1.15，D正确。",
        "index": 59
    },
    {
        "type": 1,
        "id": 0,
        "name": "多选题",
        "content": "（多选题）在多年冻土地区进行勘察时，下列哪些选项说法是错误的？\r\n",
        "answer": [
            {
                "name": "A",
                "content": "宜采用小口径高速钻机\r",
                "isanswer": true
            },
            {
                "name": "B",
                "content": "确定多年冻土上限深度的勘察时间为九~十月\r",
                "isanswer": false
            },
            {
                "name": "C",
                "content": "勘探孔的深度宜超过多年冻土上限深度的1倍\r",
                "isanswer": true
            },
            {
                "name": "D",
                "content": "对于保持冻结状态设计的地基，勘探孔深度不应小于基底以下2倍的基础宽度\r",
                "isanswer": false
            }
        ],
        "detail": "\r\n【解析】根据《岩土工程勘察规范》(GB 50021-2001）第6.6.5条第1款，宜采用大口径低速钻进，A正确；根据6.6.5第7款调查工作宜在二月至五月份进行，多年冻土上限深度的勘察时间为九、十月份，B正确；根据6.6.4第3款，无论何种原则，勘探孔的深度宜超过多年冻土上限深度的1.5倍，C错误；第6.6.4条第1款，对于保持冻结状态设计的地基，勘探孔深度不应小于基底以下2倍的基础宽度，对桩基应超过桩端以下3~5m，D正确。",
        "index": 60
    },
    {
        "type": 1,
        "id": 0,
        "name": "多选题",
        "content": "（多选题）关于高频泥石流流域和发育特征表述错误的是下列哪些选项?\r\n",
        "answer": [
            {
                "name": "A",
                "content": "固体物质主要来源于沟谷的滑坡和崩塌\r",
                "isanswer": false
            },
            {
                "name": "B",
                "content": "不良地质发育严重的沟谷多发生稀性泥石流\r",
                "isanswer": true
            },
            {
                "name": "C",
                "content": "流域岸边岩层破碎，风化强烈，山体稳定性差\r",
                "isanswer": false
            },
            {
                "name": "D",
                "content": "黏性泥石流沟中下游沟床坡度不大于4%\r",
                "isanswer": true
            }
        ],
        "detail": "\r\n【解析】根据《工程地质手册》(第五版)P685表6-4-6或《岩土工程勘察规范》(GB 50021-2001)(2009年版)附录C表C.0.1，高频率泥石流沟谷的泥石流特征：固体物质主要来源于沟谷的滑坡、崩塌。除岩性因素外，滑坡、崩塌严重的沟谷多发生黏性泥石流，规模大，反之发生稀性泥石流，规模小，A正确，B错误；高频率泥石流沟谷的流域特征：多位于强烈抬升区，岩层破碎，风化强烈，山体稳定性差。泥石流堆积新鲜，无植被或仅有稀疏草丛。黏性泥石流沟中下游沟床坡度大于4%，C正确，D错误。",
        "index": 61
    },
    {
        "type": 1,
        "id": 0,
        "name": "多选题",
        "content": "（多选题）关于膨胀土的性质，下列哪些选项是错误?\r\n",
        "answer": [
            {
                "name": "A",
                "content": "当含水量一定时，上覆压力大时膨胀量大，上覆压力小时膨胀量小\r",
                "isanswer": true
            },
            {
                "name": "B",
                "content": "当上覆压力一定时，含水量高的膨胀量大，含水量小的膨胀量小\r",
                "isanswer": true
            },
            {
                "name": "C",
                "content": "当上覆压力超过膨胀力时不会产生膨胀，只会出现压缩\r",
                "isanswer": false
            },
            {
                "name": "D",
                "content": "常年地下水位以下的膨胀土的膨胀量为零\r",
                "isanswer": false
            }
        ],
        "detail": "\r\n【解析】根据《膨胀土地区建筑技术规范》(GB 50112-2013)P88条文说明5.2.8，第一款，当含水量一定时，上覆压力小时膨胀量大，上覆压力大时膨胀量小，A错误；当压力超过土的膨胀力时就不膨胀，并出现收缩，C正确；第2款，当土的上覆压力一定时，初始含水量高的土膨胀量小，初始含水量低的土膨胀量大，B错误；常年地下水位以下的膨胀土已经充分膨胀，膨胀量为零，D正确。",
        "index": 62
    },
    {
        "type": 1,
        "id": 0,
        "name": "多选题",
        "content": "（多选题）下列选项中不属于地震灾害危险性评估分级划分指标的是哪些？\r\n",
        "answer": [
            {
                "name": "A",
                "content": "地震灾害险情 ",
                "isanswer": true
            },
            {
                "name": "B",
                "content": "地质灾害灾情\r",
                "isanswer": true
            },
            {
                "name": "C",
                "content": "建设项目重要性 ",
                "isanswer": false
            },
            {
                "name": "D",
                "content": "地质环境条件复杂程度\r",
                "isanswer": false
            }
        ],
        "detail": "\r\n【解析】根据《地质灾害危险性评估规范》(DZ/T 0286-2015)第4.3.8条，地质灾害危险性评估分级，根据地质环境条件复杂程度和建设项目重要性划分为三级，不含A和B。",
        "index": 63
    },
    {
        "type": 1,
        "id": 0,
        "name": "多选题",
        "content": "（多选题）下列关于测定黄土湿陷起始压力表述正确的是哪些选项?\r\n",
        "answer": [
            {
                "name": "A",
                "content": "测定黄土湿陷起始压力的方法只能采取原状土样进行室内压缩试验\r",
                "isanswer": false
            },
            {
                "name": "B",
                "content": "室内试验测定黄土湿陷起始压力的环刀内径不应小于79.8mm\r",
                "isanswer": true
            },
            {
                "name": "C",
                "content": "单线法压缩试验环刀试样不应少于3个，双线法环刀试样不应少于2个\r",
                "isanswer": false
            },
            {
                "name": "D",
                "content": "室内试验测定黄土湿陷起始压力，试样稳定标准为每小时变形量不大于0.01mm\r",
                "isanswer": true
            }
        ],
        "detail": "\r\n【解析】根据《湿陷性黄土地区建筑标准》(GB 50025-2018)第4.4.5条，黄土湿陷性起始压力可按现场静载荷试验和室内压缩试验结果确定，A错误；根据第4.3.1条第2款，环刀面积不应小于5000mm²，B正确；第4.3.4条第5款，单线法压缩试验不应少于5个环刀试验，C错误；第4.3.1条第5款，试样浸水前和浸水后的稳定标准，应为下沉量不大于0.01mm/h，D正确。",
        "index": 64
    },
    {
        "type": 1,
        "id": 0,
        "name": "多选题",
        "content": "（多选题）下列关于地质灾害的治理的说法中哪些是正确的?\r\n",
        "answer": [
            {
                "name": "A",
                "content": "因自然因素造成的特大型地质灾害，确需治理的，由国务院国土资源主管部门会同灾害发生的省、自治区、直辖市人民政府组织治理\r",
                "isanswer": true
            },
            {
                "name": "B",
                "content": "因自然因素造成的跨行政区域的地质灾害，确需治理的，由所跨行政区域的地方人民政府国土资源主管部门共同组织治理\r",
                "isanswer": true
            },
            {
                "name": "C",
                "content": "因工程建设等人为活动引发的地质灾害，由灾害发生地的省、自治区、直辖市人民政府组织治理\r",
                "isanswer": false
            },
            {
                "name": "D",
                "content": "地质灾害治理工程的确定，应当与地质灾害形成的成因、规模以及对人民生命和财产安全的危害程度相适应\r",
                "isanswer": true
            }
        ],
        "detail": "\r\n【解析】根据《地质灾害防治条例》第三十四条，因自然因素造成的特大型地质灾害，确需治理的，由国务院国土资源主管部门会同灾害发生地的省、自治区、直辖市人民政府组织治理；因自然因素造成的其他地质灾害，确需治理的，在县级以上地方人民政府的领导下，由本级人民政府国土资源主管部门组织治理。因自然因素造成的跨行政区域的地质灾害，确需治理的，由所跨行政区域的地方人民政府国土资源主管部门共同组织治理，A、B正确；第三十五条，因工程建设等人为活动引发的地质灾害，由责任单位承担治理责任，C错误；第三十六条，地质灾害治理工程的确定，应当与地质灾害形成的原因、规模以及对人民生命和财产安全的危害程度相适应，D正确。",
        "index": 65
    },
    {
        "type": 1,
        "id": 0,
        "name": "多选题",
        "content": "（多选题）招标人有下列哪些行为并影响中标结果的，应判为中标无效?\r\n",
        "answer": [
            {
                "name": "A",
                "content": "排斥潜在投标人\r",
                "isanswer": false
            },
            {
                "name": "B",
                "content": "向他人透露己获取招标文件的潜在投标人的名称、数量\r",
                "isanswer": true
            },
            {
                "name": "C",
                "content": "强制要求投标人组成的联合共同投标的\r",
                "isanswer": false
            },
            {
                "name": "D",
                "content": "在确定中标人前，招标人与投标人就投标价格进行谈判\r",
                "isanswer": true
            }
        ],
        "detail": "\r\n【解析】根据《中华人民共和国招标投标法》第五十二条，依法必须进行招标的项目的招标人向他人透露已获取招标文件的潜在投标人的名称、数量或者可能影响公平竞争的有关招标投标的其他情况的，或者泄露标底的，影响中标结果的，中标无效，B正确；第五十五条，依法必须进行招标的项目，招标人违反本法规定，与投标人就投标价格、投标方案等实质性内容进行谈判的，影响中标结果的，中标无效，D正确；第五十一条，招标人以不合理的条件限制或者排斥潜在投标人的，对潜在投标人实行歧视待遇的，强制要求投标人组成联合体共同投标的，或者限制投标人之间竞争的，责令改正，可以处一万元以上五万元以下的罚款，A、C错误。",
        "index": 66
    },
    {
        "type": 1,
        "id": 0,
        "name": "多选题",
        "content": "（多选题）关于工程监理单位、监理人员，下列哪些说法是正确的?\r\n",
        "answer": [
            {
                "name": "A",
                "content": "工程监理单位与被监理工程的承包单位以及建筑材料、建筑构配件和设备供应单位不得有隶属关系或者其他利害关系\r",
                "isanswer": true
            },
            {
                "name": "B",
                "content": "工程监理单位与承包单位串通，为承包单位谋取非法利益，给建设单位造成损失的，应当与承包单位承担连带赔偿责任\r",
                "isanswer": true
            },
            {
                "name": "C",
                "content": "工程监理人员认为工程施工不符合工作设计要求、施工技术标准和合同约定的，有权要求建筑施工企业改正\r",
                "isanswer": true
            },
            {
                "name": "D",
                "content": "工程监理人员发现工程设计不符合建筑工程质量标准或者合同约定的质量要求，有权要求设计单位改正\r",
                "isanswer": false
            }
        ],
        "detail": "\r\n【解析】根据《中华人民共和国建筑法》第三十四条，工程监理单位与被监理工程的承包单位以及建筑材料、建筑构配件和设备供应单位不得有隶属关系或者其他利害关系，A正确；第三十五条，工程监理单位与承包单位串通，为承包单位谋取非法利益，给建设单位造成损失的，应当与承包单位承担连带赔偿责任，B正确；第三十二条，工程监理人员认为工程施工不符合工程设计要求、施工技术标准和合同约定的，有权要求建筑施工企业改正，C正确；工程监理人员发现工程设计不符合建筑工程质量标准或者合同约定的质量要求的，应当报告建设单位要求设计单位改正，D错误。",
        "index": 67
    },
    {
        "type": 1,
        "id": 0,
        "name": "多选题",
        "content": "（多选题）关于要约生效、要约撤回、要约撤销的说法，下列哪些表述是正确的?\r\n",
        "answer": [
            {
                "name": "A",
                "content": "采用数据电文形式订立合同，收件人指定特定系统接收数据电文的，该数据电文进入该特定系统的时间，视为到达时间，要约生效\r",
                "isanswer": true
            },
            {
                "name": "B",
                "content": "未指定特定系统的，该数据电文进入收件人的任何系统，收件人访问时间视为到达时间，要约生效\r",
                "isanswer": false
            },
            {
                "name": "C",
                "content": "撤回要约的通知应当在要约到达受要约人之前或者与要约同时到达受要约人\r",
                "isanswer": true
            },
            {
                "name": "D",
                "content": "撤销要约的通知应当在受要约人发出承诺通知之后到达受要约人\r",
                "isanswer": false
            }
        ],
        "detail": "\r\n【解析】根据《中华人民共和国合同法》第二章第十六条，要约到达受要约人时生效，采用数据电文形式订立合同，收件人指定特定系统接收数据电文的，该数据电文进入该特定系统的时间，视为到达时间，A正确；未指定特定系统的，该数据电文进入收件人的任何系统的首次时间，视为到达时间，B错误；第十七条，要约可以撤回，撤回要约的通知应当在要约到达受要约人之前或者与要约同时到达受要约人，C正确；第十八条，要约可以撤销。撤销要约的通知应当在受要约人发出承诺通知之前到达受要约人，D错误。",
        "index": 68
    },
    {
        "type": 1,
        "id": 0,
        "name": "多选题",
        "content": "（多选题）根据住房城乡建设部办公厅关于实施《危险性较大的分部分项工程安全管理规定》有关问题的通知(建办质[2018]31号)的规定，下列危大工程专项施工方案的评审专家基本条件哪些是正确的?\r\n",
        "answer": [
            {
                "name": "A",
                "content": "诚实守信、作风正派、学术严谨\r",
                "isanswer": true
            },
            {
                "name": "B",
                "content": "具有注册土木工程师（岩土）或注册结构工程师资格\r",
                "isanswer": false
            },
            {
                "name": "C",
                "content": "从事相关专业工作15年以上或具有丰富的专业经验\r",
                "isanswer": true
            },
            {
                "name": "D",
                "content": "具有高级专业技术职称\r",
                "isanswer": true
            }
        ],
        "detail": "\r\n【解析】根据住房城乡建设部办公厅关于实施《危险性较大的分部分项工程安全管理规定》有关问题的通知(建办质[2018]31号)第八条，专家库专家应当具备以下基本条件：（一）诚实守信、作风正派、学术严谨；（二）从事相关专业工作15年以上或具有丰富的专业经验；（三）具有高级专业技术职称。超出当年指定考试大纲。",
        "index": 69
    },
    {
        "type": 1,
        "id": 0,
        "name": "多选题",
        "content": "（多选题）根据《注册土木工程师(岩土)执业及管理工作暂行规定》(建设部建市[2009]105号)，下列哪些选项不符合注册土木工程师(岩土)执业管理规定要求?\r\n",
        "answer": [
            {
                "name": "A",
                "content": "注册土木工程师(岩土)必须受聘并注册于一个建设工程勘察、设计、检测、施工、监理、施工图审查、招标代理、造价咨询等单位方能执业\r",
                "isanswer": false
            },
            {
                "name": "B",
                "content": "注册土木工程师(岩土)可以注册土术工程师(岩土)的名义在全国范围内从事相关专业活动，其执业范围不受其聘用单位的业务范围限制\r",
                "isanswer": true
            },
            {
                "name": "C",
                "content": "注册土木工程师（岩土）在执业过程中，应及时、独立地在规定的岩土工程技术文件上签章，聘用单位不得强迫注册土木工程师(岩土)在工程技术文件中签章\r",
                "isanswer": false
            },
            {
                "name": "D",
                "content": "注册土木工程师(岩土)注册年龄不允许超过70岁\r",
                "isanswer": true
            }
        ],
        "detail": "\r\n【解析】根据《注册土木工程师(岩土)执业及管理工作暂行规定》(建设部建市[2009]105号)三、执业管理（一）条，A正确；（二）条，注册土木工程师（岩土）执业范围不得超越其聘用单位的业务范围，当与其聘用单位的业务范围不符时，个人执业范围应服从聘用单位的业务范围，B错误；（七）条，C正确；（十一）条，注册土木工程师（岩土）注册年龄一般不得超过70岁。对超过70岁的注册土木工程师（岩土），注册部门原则上不再办理延续注册手续。个别年龄达到70岁，但身体状况良好、能完全胜任工作的注册土木工程师（岩土），由本人自愿提出申请，经省级以上建设行政主管部门批准，可以继续受聘执业，D错误。",
        "index": 70
    }
]